{
	"_id": "5e6e82d689f31c036cc95115",
	"coordinates": [],
	"reviews": [],
	"title": "qui",
	"price": 50315,
	"description": "Eum ullam explicabo aut.\nIllo nihil nobis et atque.",
	"images": [{
		"_id": "5e6e82d689f31c036cc95116",
		"url": "https://i.picsum.photos/id/703/600/600.jpg"
	}],
	"location": "West Zackaryport",
	"author": "5e691d837c30c848fc8b886d",
	"__v": 0
} {
	"_id": "5e6e82d689f31c036cc95117",
	"coordinates": [],
	"reviews": [],
	"title": "esse",
	"price": 37353,
	"description": "ut nam ut",
	"images": [{
		"_id": "5e6e82d689f31c036cc95118",
		"url": "https://i.picsum.photos/id/703/600/600.jpg"
	}],
	"location": "West Miller",
	"author": "5e691d837c30c848fc8b886d",
	"__v": 0
} {
	"_id": "5e6e82d689f31c036cc95119",
	"coordinates": [],
	"reviews": [],
	"title": "explicabo",
	"price": 9338,
	"description": "Iure assumenda quod repellendus tempora facere dolorem sint aut. Sapiente et quo quo quas eum optio quia assumenda. Et qui tempore et quod aut dolore qui perferendis cumque.\n \rOptio debitis vel. Ea maiores vel et est. Iusto enim voluptas.\n \rDistinctio occaecati sed aut numquam illo odit. Et enim praesentium sed sit excepturi id deleniti repellendus eos. Consequatur et quos 
	vel et dolorem ad.Sit aut saepe nemo et atque molestias tempore in quae.Eos voluptas consequatur.Sit aliquam voluptatem dolores sit numquam sint.
	",
	"images": [{
		"_id": "5e6e82d689f31c036cc9511a",
		"url": "https://i.picsum.photos/id/703/600/600.jpg"
	}],
	"location": "Schadenport",
	"author": "5e691d837c30c848fc8b886d",
	"__v": 0
} {
	"_id": "5e6e82d689f31c036cc9511b",
	"coordinates": [],
	"reviews": [],
	"title": "eaque",
	"price": 27617,
	"description": "Est iste labore. Velit dolore sed culpa ea animi aut qui autem. Ipsa fugiat perspiciatis eum eos id nemo. Ad delectus quia odio sunt dignissimos enim id incidunt. Fugit voluptate eos eos illum. Culpa dolores ut.\n \rQuasi dicta voluptas reprehenderit labore dolore. Nemo neque delectus. Aut sint sequi.\n \rVeritatis in et quo voluptatem. Quod fuga sed eos adipisci et dolor rerum rem voluptate. Molestias est pariatur veritatis magnam repellat laboriosam. Aut 
	et impedit soluta architecto dolores.
	",
	"images": [{
		"_id": "5e6e82d689f31c036cc9511c",
		"url": "https://i.picsum.photos/id/703/600/600.jpg"
	}],
	"location": "Marieview",
	"author": "5e691d837c30c848fc8b886d",
	"__v": 0
} {
	"_id": "5e6e82d689f31c036cc9511d",
	"coordinates": [],
	"reviews": [],
	"title": "voluptatum",
	"price": 48167,
	"description": "Et qui soluta nulla quod mollitia ullam. Libero exercitationem et ex non sed reprehenderit veniam. Suscipit nam enim qui dolor voluptates qui et aut a. Vel minus voluptas dicta voluptatum. Mollitia assumenda sit eos porro animi.",
	"images": [{
		"_id": "5e6e82d689f31c036cc9511e",
		"url": "https://i.picsum.photos/id/703/600/600.jpg"
	}],
	"location": "Metzstad",
	"author": "5e691d837c30c848fc8b886d",
	"__v": 0
} {
	"_id": "5e6e82d689f31c036cc9511f",
	"coordinates": [],
	"reviews": [],
	"title": "quasi",
	"price": 8920,
	"description": "Voluptate eius eum optio voluptas voluptatum ipsam architecto sapiente. Vero consectetur rem quis officiis nesciunt eveniet maxime. Error iure dolorem. Laudantium non culpa.",
	"images": [{
		"_id": "5e6e82d689f31c036cc95120",
		"url": "https://i.picsum.photos/id/703/600/600.jpg"
	}],
	"location": "Lawrenceport",
	"author": "5e691d837c30c848fc8b886d",
	"__v": 0
} {
	"_id": "5e6e82d689f31c036cc95121",
	"coordinates": [],
	"reviews": [],
	"title": "molestias",
	"price": 31325,
	"description": "Ut est voluptatum laborum nihil autem quis qui.\nUt aut 
	nemo.\nTotam officia voluptatum quisquam sed omnis animi.
	",
	"images": [{
		"_id": "5e6e82d689f31c036cc95122",
		"url": "https://i.picsum.photos/id/703/600/600.jpg"
	}],
	"location": "East Curt",
	"author": "5e691d837c30c848fc8b886d",
	"__v": 0
} {
	"_id": "5e6e82d689f31c036cc95123",
	"coordinates": [],
	"reviews": [],
	"title": "et",
	"price": 74494,
	"description": "Qui et quibusdam et enim est ipsa. Sunt ut sequi dignissimos. Itaque est illum itaque omnis qui nostrum laboriosam animi sunt. Inventore 
	tenetur nostrum esse illo voluptatem eum id repellat.Dignissimos et illum quasi
	sed ea ipsa quisquam architecto.Delectus amet facilis sint eos voluptates qui omnis eaque est.
	",
	"images": [{
		"_id": "5e6e82d689f31c036cc95124",
		"url": "https://i.picsum.photos/id/703/600/600.jpg"
	}],
	"location": "Port Minervaberg",
	"author": "5e691d837c30c848fc8b886d",
	"__v": 0
} {
	"_id": "5e6e82d689f31c036cc95125",
	"coordinates": [],
	"reviews": [],
	"title": "et",
	"price": 92671,
	"description": "Nostrum itaque qui ut officia consequatur et voluptas.\nCorrupti quia sit debitis dolores adipisci ullam architecto.\nNesciunt cum et impedit id placeat ab et libero esse.\nEum cupiditate voluptas quo est est eos dolorem.",
	"images": [{
		"_id": "5e6e82d689f31c036cc95126",
		"url": "https://i.picsum.photos/id/703/600/600.jpg"
	}],
	"location": "Fritzshire",
	"author": "5e691d837c30c848fc8b886d",
	"__v": 0
} {
	"_id": "5e6e82d689f31c036cc95127",
	"coordinates": [],
	"reviews": [],
	"title": "placeat",
	"price": 86333,
	"description": "Eaque quis odio dolores ducimus odit recusandae repellat consequatur perspiciatis.\nCulpa voluptatem ipsum magnam inventore eos corporis 
	eum earum earum.\nIncidunt voluptatem quo fuga sed.\nQuae maiores dolore dolorum
	soluta incidunt enim neque adipisci aliquam.
	",
	"images": [{
		"_id": "5e6e82d689f31c036cc95128",
		"url": "https://i.picsum.photos/id/703/600/600.jpg"
	}],
	"location": "Eldonfurt",
	"author": "5e691d837c30c848fc8b886d",
	"__v": 0
} {
	"_id": "5e6e82d689f31c036cc95129",
	"coordinates": [],
	"reviews": [],
	"title": "vero",
	"price": 43517,
	"description": "Aliquam dolor id labore laudantium enim.",
	"images": [{
		"_id": "5e6e82d689f31c036cc9512a",
		"url": "https://i.picsum.photos/id/703/600/600.jpg"
	}],
	"location": "McCulloughhaven",
	"author": "5e691d837c30c848fc8b886d",
	"__v": 0
} {
	"_id": "5e6e82d689f31c036cc9512b",
	"coordinates": [],
	"reviews": [],
	"title": "in",
	"price": 79383,
	"description": "Illo quae et accusantium quam.",
	"images": [{
		"_id": "5e6e82d689f31c036cc9512c",
		"url": "https://i.picsum.photos/id/703/600/600.jpg"
	}],
	"location": "North Destinmouth",
	"author": "5e691d837c30c848fc8b886d",
	"__v": 0
} {
	"_id": "5e6e82d689f31c036cc9512d",
	"coordinates": [],
	"reviews": [],
	"title": "provident",
	"price": 67947,
	"description": "Quod consequuntur tempore corporis. Nesciunt voluptatem 
	consequuntur excepturi porro.Mollitia aliquam esse eum repudiandae et.Tempore voluptatem labore eum accusantium.Alias repudiandae animi deserunt quibusdam dolores consequuntur.Recusandae libero aut qui inventore.
	",
	"images": [{
		"_id": "5e6e82d689f31c036cc9512e",
		"url": "https://i.picsum.photos/id/703/600/600.jpg"
	}],
	"location": "Markborough",
	"author": "5e691d837c30c848fc8b886d",
	"__v": 0
} {
	"_id": "5e6e82d689f31c036cc9512f",
	"coordinates": [],
	"reviews": [],
	"title": "nemo",
	"price": 13684,
	"description": "Quaerat omnis hic rem. Provident aut dolor. Aliquid quisquam consequuntur deserunt expedita totam expedita. Est unde culpa. Aut recusandae ipsum et autem. Possimus magni nemo reprehenderit non est non ex ipsa et.\n \rMagni laudantium velit minus aut qui. Molestias dignissimos rem dolor fuga. Quia ut odit labore rerum dolorem itaque id. Quod necessitatibus est aliquid. Provident eius et sunt modi eos aut reiciendis.\n \rEt sit voluptatem voluptatem. Mollitia inventore non libero fugiat neque laborum. Et quia voluptas libero odio. Sequi sed libero voluptas. Adipisci neque illo molestiae.",
	"images": [{
		"_id": "5e6e82d689f31c036cc95130",
		"url": "https://i.picsum.photos/id/703/600/600.jpg"
	}],
	"location": "South Darron",
	"author": "5e691d837c30c848fc8b886d",
	"__v": 0
} {
	"_id": "5e6e82d689f31c036cc95131",
	"coordinates": [],
	"reviews": [],
	"title": "earum",
	"price": 63659,
	"description": "Et itaque velit. Nobis reiciendis voluptas aut quidem id ipsa ipsa voluptas. Quod laudantium quo tempore.",
	"images": [{
		"_id": "5e6e82d689f31c036cc95132",
		"url": "https://i.picsum.photos/id/703/600/600.jpg"
	}],
	"location": "Krajcikhaven",
	"author": "5e691d837c30c848fc8b886d",
	"__v": 0
} {
	"_id": "5e6e82d689f31c036cc95133",
	"coordinates": [],
	"reviews": [],
	"title": "adipisci",
	"price": 46370,
	"description": "ut",
	"images": [{
		"_id": "5e6e82d689f31c036cc95134",
		"url": "https://i.picsum.photos/id/703/600/600.jpg"
	}],
	"location": "Joesphstad",
	"author": "5e691d837c30c848fc8b886d",
	"__v": 0
} {
	"_id": "5e6e82d689f31c036cc95135",
	"coordinates": [],
	"reviews": [],
	"title": "et",
	"price": 66895,
	"description": "Dicta aut odit quia enim vitae voluptatibus illum. Odio 
	voluptas et animi iure et.
	",
	"images": [{
		"_id": "5e6e82d689f31c036cc95136",
		"url": "https://i.picsum.photos/id/703/600/600.jpg"
	}],
	"location": "New Jerald",
	"author": "5e691d837c30c848fc8b886d",
	"__v": 0
} {
	"_id": "5e6e82d689f31c036cc95137",
	"coordinates": [],
	"reviews": [],
	"title": "ut",
	"price": 33705,
	"description": "Ut beatae illo sunt qui harum atque ipsa aut voluptas.\nNobis distinctio necessitatibus nesciunt asperiores et dolor cumque provident qui.\nNeque vel delectus quia quo nam aut debitis.",
	"images": [{
		"_id": "5e6e82d689f31c036cc95138",
		"url": "https://i.picsum.photos/id/703/600/600.jpg"
	}],
	"location": "Feeneystad",
	"author": "5e691d837c30c848fc8b886d",
	"__v": 0
} {
	"_id": "5e6e82d689f31c036cc95139",
	"coordinates": [],
	"reviews": [],
	"title": "necessitatibus",
	"price": 10690,
	"description": "minus veniam impedit",
	"images": [{
		"_id": "5e6e82d689f31c036cc9513a",
		"url": "https://i.picsum.photos/id/703/600/600.jpg"
	}],
	"location": "East Reyeshaven",
	"author": "5e691d837c30c848fc8b886d",
	"__v": 0
} {
	"_id": "5e6e82d689f31c036cc9513b",
	"coordinates": [],
	"reviews": [],
	"title": "et",
	"price": 75972,
	"description": "nisi",
	"images": [{
		"_id": "5e6e82d689f31c036cc9513c",
		"url": "https://i.picsum.photos/id/703/600/600.jpg"
	}],
	"location": "Port Alek",
	"author": "5e691d837c30c848fc8b886d",
	"__v": 0
} {
	"_id": "5e6e82d689f31c036cc9513d",
	"coordinates": [],
	"reviews": [],
	"title": "cumque",
	"price": 52470,
	"description": "suscipit dolorum repellat",
	"images": [{
		"_id": "5e6e82d689f31c036cc9513e",
		"url": "https://i.picsum.photos/id/703/600/600.jpg"
	}],
	"location": "Robertaton",
	"author": "5e691d837c30c848fc8b886d",
	"__v": 0
} {
	"_id": "5e6e82d689f31c036cc9513f",
	"coordinates": [],
	"reviews": [],
	"title": "dolore",
	"price": 63735,
	"description": "dolorum dicta reprehenderit",
	"images": [{
		"_id": "5e6e82d689f31c036cc95140",
		"url": "https://i.picsum.photos/id/703/600/600.jpg"
	}],
	"location": "Torpland",
	"author": "5e691d837c30c848fc8b886d",
	"__v": 0
} {
	"_id": "5e6e82d689f31c036cc95141",
	"coordinates": [],
	"reviews": [],
	"title": "ipsam",
	"price": 75283,
	"description": "Voluptatem voluptatum deleniti explicabo mollitia. Quia 
	rerum temporibus illum.Aut in quia aut rerum.Velit saepe dolor nesciunt debitis non omnis recusandae odit eligendi.Dolores dolores et maxime perspiciatis incidunt totam omnis laborum officia.
	",
	"images": [{
		"_id": "5e6e82d689f31c036cc95142",
		"url": "https://i.picsum.photos/id/703/600/600.jpg"
	}],
	"location": "Lake Cristalstad",
	"author": "5e691d837c30c848fc8b886d",
	"__v": 0
} {
	"_id": "5e6e82d689f31c036cc95143",
	"coordinates": [],
	"reviews": [],
	"title": "deleniti",
	"price": 78500,
	"description": "Aut facilis tenetur dolore placeat dolorum ut.",
	"images": [{
		"_id": "5e6e82d689f31c036cc95144",
		"url": "https://i.picsum.photos/id/703/600/600.jpg"
	}],
	"location": "Kulasburgh",
	"author": "5e691d837c30c848fc8b886d",
	"__v": 0
} {
	"_id": "5e6e82d689f31c036cc95145",
	"coordinates": [],
	"reviews": [],
	"title": "maxime",
	"price": 15152,
	"description": "Quia sapiente debitis eligendi odit.",
	"images": [{
		"_id": "5e6e82d689f31c036cc95146",
		"url": "https://i.picsum.photos/id/703/600/600.jpg"
	}],
	"location": "Framifort",
	"author": "5e691d837c30c848fc8b886d",
	"__v": 0
} {
	"_id": "5e6e82d689f31c036cc95147",
	"coordinates": [],
	"reviews": [],
	"title": "delectus",
	"price": 6641,
	"description": "Assumenda fugiat adipisci qui omnis ut debitis vero aut. Ducimus nihil laudantium sit id voluptates. Eum eum commodi rerum voluptas nam. 
	Unde numquam facere aut quas enim aliquam.Possimus earum voluptas.\n\ rDucimus et eaque voluptatum voluptas nihil quaerat ducimus.Porro eum ut maxime perspiciatis iusto omnis sequi autem dicta.Cumque ut nihil a quas autem consequuntur.Sunt odio voluptate ea reprehenderit non nemo.Ut atque occaecati fugiat doloribus a
	doloremque.\n\ rLaboriosam excepturi porro ut porro quasi qui nihil id.Et ut corporis tempora voluptatem mollitia ut.Magnam voluptatem tempore dignissimos necessitatibus quas sit error quo.
	",
	"images": [{
		"_id": "5e6e82d689f31c036cc95148",
		"url": "https://i.picsum.photos/id/703/600/600.jpg"
	}],
	"location": "Dickensfurt",
	"author": "5e691d837c30c848fc8b886d",
	"__v": 0
} {
	"_id": "5e6e82d689f31c036cc95149",
	"coordinates": [],
	"reviews": [],
	"title": "earum",
	"price": 93878,
	"description": "Vero alias ut architecto sint laboriosam quia veritatis 
	esse et.
	",
	"images": [{
		"_id": "5e6e82d689f31c036cc9514a",
		"url": "https://i.picsum.photos/id/703/600/600.jpg"
	}],
	"location": "Croninland",
	"author": "5e691d837c30c848fc8b886d",
	"__v": 0
} {
	"_id": "5e6e82d689f31c036cc9514b",
	"coordinates": [],
	"reviews": [],
	"title": "nihil",
	"price": 14805,
	"description": "Est sint possimus totam sunt qui dolorem reprehenderit. 
	Et eos ratione.
	",
	"images": [{
		"_id": "5e6e82d689f31c036cc9514c",
		"url": "https://i.picsum.photos/id/703/600/600.jpg"
	}],
	"location": "Jaylenshire",
	"author": "5e691d837c30c848fc8b886d",
	"__v": 0
} {
	"_id": "5e6e82d689f31c036cc9514d",
	"coordinates": [],
	"reviews": [],
	"title": "laboriosam",
	"price": 58824,
	"description": "enim ducimus ut",
	"images": [{
		"_id": "5e6e82d689f31c036cc9514e",
		"url": "https://i.picsum.photos/id/703/600/600.jpg"
	}],
	"location": "East Lesliemouth",
	"author": "5e691d837c30c848fc8b886d",
	"__v": 0
} {
	"_id": "5e6e82d689f31c036cc9514f",
	"coordinates": [],
	"reviews": [],
	"title": "explicabo",
	"price": 43735,
	"description": "Eos rerum rerum architecto quia ipsam voluptatem dolor optio.",
	"images": [{
		"_id": "5e6e82d689f31c036cc95150",
		"url": "https://i.picsum.photos/id/703/600/600.jpg"
	}],
	"location": "North Schuyler",
	"author": "5e691d837c30c848fc8b886d",
	"__v": 0
} {
	"_id": "5e6e82d689f31c036cc95151",
	"coordinates": [],
	"reviews": [],
	"title": "nam",
	"price": 43080,
	"description": "Et eum corporis suscipit. Ut amet perferendis ab eos minima qui. Rerum excepturi quo est. In consequatur velit architecto et nisi ratione. Qui possimus illo facilis minus vel dolores nisi sit illum. Optio porro laboriosam odit hic facilis reiciendis sint minima harum.\n \rCommodi incidunt voluptatem et laborum maiores. Quas sunt nihil hic aut sed non neque. Sunt assumenda vel aut et in adipisci. Voluptatem quam eum dolorem et enim quo saepe.\n \rEst eligendi veritatis commodi voluptas expedita qui libero quisquam architecto. Minus ut eum sit est quibusdam qui nemo commodi. Omnis tenetur ut eius dolores. Fuga qui saepe impedit mollitia similique mollitia et illo quis. Sit reprehenderit ea ut excepturi aut. Libero quibusdam soluta et quia culpa culpa.",
	"images": [{
		"_id": "5e6e82d689f31c036cc95152",
		"url": "https://i.picsum.photos/id/703/600/600.jpg"
	}],
	"location": "Heathcotechester",
	"author": "5e691d837c30c848fc8b886d",
	"__v": 0
} {
	"_id": "5e6e82d689f31c036cc95153",
	"coordinates": [],
	"reviews": [],
	"title": "voluptatem",
	"price": 87871,
	"description": "Et ipsa distinctio.\nNihil nihil laudantium voluptates.",
	"images": [{
		"_id": "5e6e82d689f31c036cc95154",
		"url": "https://i.picsum.photos/id/703/600/600.jpg"
	}],
	"location": "South Filibertoside",
	"author": "5e691d837c30c848fc8b886d",
	"__v": 0
} {
	"_id": "5e6e82d689f31c036cc95155",
	"coordinates": [],
	"reviews": [],
	"title": "ut",
	"price": 58592,
	"description": "et consequuntur ex",
	"images": [{
		"_id": "5e6e82d689f31c036cc95156",
		"url": "https://i.picsum.photos/id/703/600/600.jpg"
	}],
	"location": "Framibury",
	"author": "5e691d837c30c848fc8b886d",
	"__v": 0
} {
	"_id": "5e6e82d689f31c036cc95157",
	"coordinates": [],
	"reviews": [],
	"title": "amet",
	"price": 67045,
	"description": "enim saepe doloribus",
	"images": [{
		"_id": "5e6e82d689f31c036cc95158",
		"url": "https://i.picsum.photos/id/703/600/600.jpg"
	}],
	"location": "East Virginie",
	"author": "5e691d837c30c848fc8b886d",
	"__v": 0
} {
	"_id": "5e6e82d689f31c036cc95159",
	"coordinates": [],
	"reviews": [],
	"title": "voluptatibus",
	"price": 97353,
	"description": "sequi vitae vero",
	"images": [{
		"_id": "5e6e82d689f31c036cc9515a",
		"url": "https://i.picsum.photos/id/703/600/600.jpg"
	}],
	"location": "North Dariomouth",
	"author": "5e691d837c30c848fc8b886d",
	"__v": 0
} {
	"_id": "5e6e82d689f31c036cc9515b",
	"coordinates": [],
	"reviews": [],
	"title": "corrupti",
	"price": 81618,
	"description": "Quia impedit sunt deserunt aliquid praesentium et illum.",
	"images": [{
		"_id": "5e6e82d689f31c036cc9515c",
		"url": "https://i.picsum.photos/id/703/600/600.jpg"
	}],
	"location": "Port Devonteton",
	"author": "5e691d837c30c848fc8b886d",
	"__v": 0
} {
	"_id": "5e6e82d689f31c036cc9515d",
	"coordinates": [],
	"reviews": [],
	"title": "sapiente",
	"price": 17692,
	"description": "Et ea est velit quam.\nMaxime numquam numquam enim quam 
	enim quasi veritatis esse culpa.\nPerspiciatis magni atque unde natus consequatur consequatur et iusto distinctio.\nLabore ut iusto veritatis architecto hic blanditiis.\nEos aperiam maiores velit.
	",
	"images": [{
		"_id": "5e6e82d689f31c036cc9515e",
		"url": "https://i.picsum.photos/id/703/600/600.jpg"
	}],
	"location": "Baumbachburgh",
	"author": "5e691d837c30c848fc8b886d",
	"__v": 0
} {
	"_id": "5e6e82d689f31c036cc9515f",
	"coordinates": [],
	"reviews": [],
	"title": "ut",
	"price": 88871,
	"description": "consequuntur officia illo",
	"images": [{
		"_id": "5e6e82d689f31c036cc95160",
		"url": "https://i.picsum.photos/id/703/600/600.jpg"
	}],
	"location": "North Clarkmouth",
	"author": "5e691d837c30c848fc8b886d",
	"__v": 0
} {
	"_id": "5e6e82d689f31c036cc95161",
	"coordinates": [],
	"reviews": [],
	"title": "fugiat",
	"price": 3342,
	"description": "quasi quibusdam id",
	"images": [{
		"_id": "5e6e82d689f31c036cc95162",
		"url": "https://i.picsum.photos/id/703/600/600.jpg"
	}],
	"location": "Marjorietown",
	"author": "5e691d837c30c848fc8b886d",
	"__v": 0
} {
	"_id": "5e6e82d689f31c036cc95163",
	"coordinates": [],
	"reviews": [],
	"title": "ipsa",
	"price": 34081,
	"description": "ab",
	"images": [{
		"_id": "5e6e82d689f31c036cc95164",
		"url": "https://i.picsum.photos/id/703/600/600.jpg"
	}],
	"location": "North Antoniaton",
	"author": "5e691d837c30c848fc8b886d",
	"__v": 0
}